{"id":"c6b772e0-4ca8-4810-b237-1c4b414137d3","title":"AR Paper","desc":null,"updated":1659412148067,"created":1615482779163,"custom":{},"fname":"rethinking-media.reading.ar-paper","type":"note","vault":{"fsPath":"vault"},"contentHash":"8c90c35b60cb5bd402cbe02060b1ba4d","links":[{"type":"wiki","from":{"fname":"rethinking-media.reading.ar-paper","id":"c6b772e0-4ca8-4810-b237-1c4b414137d3","vaultName":"vault"},"value":"theory.materiality","position":{"start":{"line":29,"column":1,"offset":2835},"end":{"line":29,"column":23,"offset":2857},"indent":[]},"xvault":false,"sameFile":false,"to":{"fname":"theory.materiality"}}],"anchors":{},"children":[],"parent":"4a3fc522-ba50-4a17-b315-c5fe7b1a14ba","data":{}}
